odoo10_addon_web_m2x_options-10.0.1.1.1-py2.7-nspkg.pth
odoo/addons/web_m2x_options/README.rst
odoo/addons/web_m2x_options/__init__.py
odoo/addons/web_m2x_options/__manifest__.py
odoo/addons/web_m2x_options/i18n/ar.po
odoo/addons/web_m2x_options/i18n/de.po
odoo/addons/web_m2x_options/i18n/es.po
odoo/addons/web_m2x_options/i18n/fi.po
odoo/addons/web_m2x_options/i18n/fr.po
odoo/addons/web_m2x_options/i18n/hr.po
odoo/addons/web_m2x_options/i18n/it.po
odoo/addons/web_m2x_options/i18n/nl_NL.po
odoo/addons/web_m2x_options/i18n/pt_BR.po
odoo/addons/web_m2x_options/i18n/sl.po
odoo/addons/web_m2x_options/i18n/tr.po
odoo/addons/web_m2x_options/static/description/icon.png
odoo/addons/web_m2x_options/static/description/index.html
odoo/addons/web_m2x_options/static/src/js/form.js
odoo/addons/web_m2x_options/static/src/xml/base.xml
odoo/addons/web_m2x_options/views/view.xml
odoo10_addon_web_m2x_options-10.0.1.1.1.dist-info/DESCRIPTION.rst
odoo10_addon_web_m2x_options-10.0.1.1.1.dist-info/METADATA
odoo10_addon_web_m2x_options-10.0.1.1.1.dist-info/RECORD
odoo10_addon_web_m2x_options-10.0.1.1.1.dist-info/WHEEL
odoo10_addon_web_m2x_options-10.0.1.1.1.dist-info/metadata.json
odoo10_addon_web_m2x_options-10.0.1.1.1.dist-info/namespace_packages.txt
odoo10_addon_web_m2x_options-10.0.1.1.1.dist-info/top_level.txt
