Metadata-Version: 2.0
Name: odoo10-addon-web-m2x-options
Version: 10.0.1.1.1
Summary: web_m2x_options
Home-page: UNKNOWN
Author: ACSONE SA/NV, 0k.io, Tecnativa, Odoo Community Association (OCA)
Author-email: support@odoo-community.org
License: AGPL-3
Platform: UNKNOWN
Classifier: Programming Language :: Python
Classifier: Framework :: Odoo
Classifier: License :: OSI Approved :: GNU Affero General Public License v3
Requires-Python: ~=2.7
Requires-Dist: odoo (<10.1dev,>=10.0)
